[
  {
    "chamber_id": "ne-legislature",
    "district_number": "1",
    "incumbent_party": null,
    "is_open_seat": false,
    "dem_median": 0.27444999999999997,
    "gop_median": 0.7091000000000001,
    "dem_incumbency_adv": 0,
    "gop_incumbency_adv": 0,
    "is_seat_up": true
  },
  {
    "chamber_id": "ne-legislature",
    "district_number": "2",
    "incumbent_party": null,
    "is_open_seat": false,
    "dem_median": 0.36895,
    "gop_median": 0.611,
    "dem_incumbency_adv": 0,
    "gop_incumbency_adv": 0,
    "is_seat_up": true
  },
  {
    "chamber_id": "ne-legislature",
    "district_number": "3",
    "incumbent_party": null,
    "is_open_seat": false,
    "dem_median": 0.4572,
    "gop_median": 0.5218,
    "dem_incumbency_adv": 0,
    "gop_incumbency_adv": 0,
    "is_seat_up": true
  },
  {
    "chamber_id": "ne-legislature",
    "district_number": "4",
    "incumbent_party": null,
    "is_open_seat": false,
    "dem_median": 0.45585,
    "gop_median": 0.5296000000000001,
    "dem_incumbency_adv": 0,
    "gop_incumbency_adv": 0,
    "is_seat_up": true
  },
  {
    "chamber_id": "ne-legislature",
    "district_number": "5",
    "incumbent_party": null,
    "is_open_seat": false,
    "dem_median": 0.58975,
    "gop_median": 0.39055,
    "dem_incumbency_adv": 0,
    "gop_incumbency_adv": 0,
    "is_seat_up": true
  },
  {
    "chamber_id": "ne-legislature",
    "district_number": "6",
    "incumbent_party": null,
    "is_open_seat": false,
    "dem_median": 0.5681,
    "gop_median": 0.4167,
    "dem_incumbency_adv": 0,
    "gop_incumbency_adv": 0,
    "is_seat_up": true
  },
  {
    "chamber_id": "ne-legislature",
    "district_number": "7",
    "incumbent_party": null,
    "is_open_seat": false,
    "dem_median": 0.68345,
    "gop_median": 0.29585,
    "dem_incumbency_adv": 0,
    "gop_incumbency_adv": 0,
    "is_seat_up": true
  },
  {
    "chamber_id": "ne-legislature",
    "district_number": "8",
    "incumbent_party": null,
    "is_open_seat": false,
    "dem_median": 0.6709499999999999,
    "gop_median": 0.30995,
    "dem_incumbency_adv": 0,
    "gop_incumbency_adv": 0,
    "is_seat_up": true
  },
  {
    "chamber_id": "ne-legislature",
    "district_number": "9",
    "incumbent_party": null,
    "is_open_seat": false,
    "dem_median": 0.7094,
    "gop_median": 0.27254999999999996,
    "dem_incumbency_adv": 0,
    "gop_incumbency_adv": 0,
    "is_seat_up": true
  },
  {
    "chamber_id": "ne-legislature",
    "district_number": "10",
    "incumbent_party": null,
    "is_open_seat": false,
    "dem_median": 0.5318499999999999,
    "gop_median": 0.45095,
    "dem_incumbency_adv": 0,
    "gop_incumbency_adv": 0,
    "is_seat_up": true
  },
  {
    "chamber_id": "ne-legislature",
    "district_number": "11",
    "incumbent_party": null,
    "is_open_seat": false,
    "dem_median": 0.8360000000000001,
    "gop_median": 0.14535,
    "dem_incumbency_adv": 0,
    "gop_incumbency_adv": 0,
    "is_seat_up": true
  },
  {
    "chamber_id": "ne-legislature",
    "district_number": "12",
    "incumbent_party": null,
    "is_open_seat": false,
    "dem_median": 0.50285,
    "gop_median": 0.4787,
    "dem_incumbency_adv": 0,
    "gop_incumbency_adv": 0,
    "is_seat_up": true
  },
  {
    "chamber_id": "ne-legislature",
    "district_number": "13",
    "incumbent_party": null,
    "is_open_seat": false,
    "dem_median": 0.6335,
    "gop_median": 0.3481,
    "dem_incumbency_adv": 0,
    "gop_incumbency_adv": 0,
    "is_seat_up": true
  },
  {
    "chamber_id": "ne-legislature",
    "district_number": "14",
    "incumbent_party": null,
    "is_open_seat": false,
    "dem_median": 0.4475,
    "gop_median": 0.53345,
    "dem_incumbency_adv": 0,
    "gop_incumbency_adv": 0,
    "is_seat_up": true
  },
  {
    "chamber_id": "ne-legislature",
    "district_number": "15",
    "incumbent_party": null,
    "is_open_seat": false,
    "dem_median": 0.3234,
    "gop_median": 0.6601,
    "dem_incumbency_adv": 0,
    "gop_incumbency_adv": 0,
    "is_seat_up": true
  },
  {
    "chamber_id": "ne-legislature",
    "district_number": "16",
    "incumbent_party": null,
    "is_open_seat": false,
    "dem_median": 0.2592,
    "gop_median": 0.7248,
    "dem_incumbency_adv": 0,
    "gop_incumbency_adv": 0,
    "is_seat_up": true
  },
  {
    "chamber_id": "ne-legislature",
    "district_number": "17",
    "incumbent_party": null,
    "is_open_seat": false,
    "dem_median": 0.34485,
    "gop_median": 0.6381,
    "dem_incumbency_adv": 0,
    "gop_incumbency_adv": 0,
    "is_seat_up": true
  },
  {
    "chamber_id": "ne-legislature",
    "district_number": "18",
    "incumbent_party": null,
    "is_open_seat": false,
    "dem_median": 0.48714999999999997,
    "gop_median": 0.49645,
    "dem_incumbency_adv": 0,
    "gop_incumbency_adv": 0,
    "is_seat_up": true
  },
  {
    "chamber_id": "ne-legislature",
    "district_number": "19",
    "incumbent_party": null,
    "is_open_seat": false,
    "dem_median": 0.20484999999999998,
    "gop_median": 0.77895,
    "dem_incumbency_adv": 0,
    "gop_incumbency_adv": 0,
    "is_seat_up": true
  },
  {
    "chamber_id": "ne-legislature",
    "district_number": "20",
    "incumbent_party": null,
    "is_open_seat": false,
    "dem_median": 0.5387500000000001,
    "gop_median": 0.4447,
    "dem_incumbency_adv": 0,
    "gop_incumbency_adv": 0,
    "is_seat_up": true
  },
  {
    "chamber_id": "ne-legislature",
    "district_number": "21",
    "incumbent_party": null,
    "is_open_seat": false,
    "dem_median": 0.4284,
    "gop_median": 0.5523,
    "dem_incumbency_adv": 0,
    "gop_incumbency_adv": 0,
    "is_seat_up": true
  },
  {
    "chamber_id": "ne-legislature",
    "district_number": "22",
    "incumbent_party": null,
    "is_open_seat": false,
    "dem_median": 0.20134999999999997,
    "gop_median": 0.7859,
    "dem_incumbency_adv": 0,
    "gop_incumbency_adv": 0,
    "is_seat_up": true
  },
  {
    "chamber_id": "ne-legislature",
    "district_number": "23",
    "incumbent_party": null,
    "is_open_seat": false,
    "dem_median": 0.2501,
    "gop_median": 0.7343,
    "dem_incumbency_adv": 0,
    "gop_incumbency_adv": 0,
    "is_seat_up": true
  },
  {
    "chamber_id": "ne-legislature",
    "district_number": "24",
    "incumbent_party": null,
    "is_open_seat": false,
    "dem_median": 0.23695,
    "gop_median": 0.7447999999999999,
    "dem_incumbency_adv": 0,
    "gop_incumbency_adv": 0,
    "is_seat_up": true
  },
  {
    "chamber_id": "ne-legislature",
    "district_number": "25",
    "incumbent_party": null,
    "is_open_seat": false,
    "dem_median": 0.46675,
    "gop_median": 0.5188,
    "dem_incumbency_adv": 0,
    "gop_incumbency_adv": 0,
    "is_seat_up": true
  },
  {
    "chamber_id": "ne-legislature",
    "district_number": "26",
    "incumbent_party": null,
    "is_open_seat": false,
    "dem_median": 0.5462,
    "gop_median": 0.42895,
    "dem_incumbency_adv": 0,
    "gop_incumbency_adv": 0,
    "is_seat_up": true
  },
  {
    "chamber_id": "ne-legislature",
    "district_number": "27",
    "incumbent_party": null,
    "is_open_seat": false,
    "dem_median": 0.5183,
    "gop_median": 0.4603,
    "dem_incumbency_adv": 0,
    "gop_incumbency_adv": 0,
    "is_seat_up": true
  },
  {
    "chamber_id": "ne-legislature",
    "district_number": "28",
    "incumbent_party": null,
    "is_open_seat": false,
    "dem_median": 0.659,
    "gop_median": 0.31965,
    "dem_incumbency_adv": 0,
    "gop_incumbency_adv": 0,
    "is_seat_up": true
  },
  {
    "chamber_id": "ne-legislature",
    "district_number": "29",
    "incumbent_party": null,
    "is_open_seat": false,
    "dem_median": 0.60565,
    "gop_median": 0.37455,
    "dem_incumbency_adv": 0,
    "gop_incumbency_adv": 0,
    "is_seat_up": true
  },
  {
    "chamber_id": "ne-legislature",
    "district_number": "30",
    "incumbent_party": null,
    "is_open_seat": false,
    "dem_median": 0.391,
    "gop_median": 0.593,
    "dem_incumbency_adv": 0,
    "gop_incumbency_adv": 0,
    "is_seat_up": true
  },
  {
    "chamber_id": "ne-legislature",
    "district_number": "31",
    "incumbent_party": null,
    "is_open_seat": false,
    "dem_median": 0.45740000000000003,
    "gop_median": 0.5279,
    "dem_incumbency_adv": 0,
    "gop_incumbency_adv": 0,
    "is_seat_up": true
  },
  {
    "chamber_id": "ne-legislature",
    "district_number": "32",
    "incumbent_party": null,
    "is_open_seat": false,
    "dem_median": 0.277,
    "gop_median": 0.70575,
    "dem_incumbency_adv": 0,
    "gop_incumbency_adv": 0,
    "is_seat_up": true
  },
  {
    "chamber_id": "ne-legislature",
    "district_number": "33",
    "incumbent_party": null,
    "is_open_seat": false,
    "dem_median": 0.25585,
    "gop_median": 0.7275499999999999,
    "dem_incumbency_adv": 0,
    "gop_incumbency_adv": 0,
    "is_seat_up": true
  },
  {
    "chamber_id": "ne-legislature",
    "district_number": "34",
    "incumbent_party": null,
    "is_open_seat": false,
    "dem_median": 0.22885,
    "gop_median": 0.7557,
    "dem_incumbency_adv": 0,
    "gop_incumbency_adv": 0,
    "is_seat_up": true
  },
  {
    "chamber_id": "ne-legislature",
    "district_number": "35",
    "incumbent_party": null,
    "is_open_seat": false,
    "dem_median": 0.36634999999999995,
    "gop_median": 0.61505,
    "dem_incumbency_adv": 0,
    "gop_incumbency_adv": 0,
    "is_seat_up": true
  },
  {
    "chamber_id": "ne-legislature",
    "district_number": "36",
    "incumbent_party": null,
    "is_open_seat": false,
    "dem_median": 0.38,
    "gop_median": 0.6032,
    "dem_incumbency_adv": 0,
    "gop_incumbency_adv": 0,
    "is_seat_up": true
  },
  {
    "chamber_id": "ne-legislature",
    "district_number": "37",
    "incumbent_party": null,
    "is_open_seat": false,
    "dem_median": 0.30025,
    "gop_median": 0.67925,
    "dem_incumbency_adv": 0,
    "gop_incumbency_adv": 0,
    "is_seat_up": true
  },
  {
    "chamber_id": "ne-legislature",
    "district_number": "38",
    "incumbent_party": null,
    "is_open_seat": false,
    "dem_median": 0.16299999999999998,
    "gop_median": 0.8229,
    "dem_incumbency_adv": 0,
    "gop_incumbency_adv": 0,
    "is_seat_up": true
  },
  {
    "chamber_id": "ne-legislature",
    "district_number": "39",
    "incumbent_party": null,
    "is_open_seat": false,
    "dem_median": 0.3752,
    "gop_median": 0.61085,
    "dem_incumbency_adv": 0,
    "gop_incumbency_adv": 0,
    "is_seat_up": true
  },
  {
    "chamber_id": "ne-legislature",
    "district_number": "40",
    "incumbent_party": null,
    "is_open_seat": false,
    "dem_median": 0.14575,
    "gop_median": 0.8402000000000001,
    "dem_incumbency_adv": 0,
    "gop_incumbency_adv": 0,
    "is_seat_up": true
  },
  {
    "chamber_id": "ne-legislature",
    "district_number": "41",
    "incumbent_party": null,
    "is_open_seat": false,
    "dem_median": 0.1754,
    "gop_median": 0.8102,
    "dem_incumbency_adv": 0,
    "gop_incumbency_adv": 0,
    "is_seat_up": true
  },
  {
    "chamber_id": "ne-legislature",
    "district_number": "42",
    "incumbent_party": null,
    "is_open_seat": false,
    "dem_median": 0.2033,
    "gop_median": 0.7808999999999999,
    "dem_incumbency_adv": 0,
    "gop_incumbency_adv": 0,
    "is_seat_up": true
  },
  {
    "chamber_id": "ne-legislature",
    "district_number": "43",
    "incumbent_party": null,
    "is_open_seat": false,
    "dem_median": 0.14945,
    "gop_median": 0.8371,
    "dem_incumbency_adv": 0,
    "gop_incumbency_adv": 0,
    "is_seat_up": true
  },
  {
    "chamber_id": "ne-legislature",
    "district_number": "44",
    "incumbent_party": null,
    "is_open_seat": false,
    "dem_median": 0.19390000000000002,
    "gop_median": 0.7939499999999999,
    "dem_incumbency_adv": 0,
    "gop_incumbency_adv": 0,
    "is_seat_up": true
  },
  {
    "chamber_id": "ne-legislature",
    "district_number": "45",
    "incumbent_party": null,
    "is_open_seat": false,
    "dem_median": 0.46699999999999997,
    "gop_median": 0.50895,
    "dem_incumbency_adv": 0,
    "gop_incumbency_adv": 0,
    "is_seat_up": true
  },
  {
    "chamber_id": "ne-legislature",
    "district_number": "46",
    "incumbent_party": null,
    "is_open_seat": false,
    "dem_median": 0.5797,
    "gop_median": 0.394,
    "dem_incumbency_adv": 0,
    "gop_incumbency_adv": 0,
    "is_seat_up": true
  },
  {
    "chamber_id": "ne-legislature",
    "district_number": "47",
    "incumbent_party": null,
    "is_open_seat": false,
    "dem_median": 0.1703,
    "gop_median": 0.8141,
    "dem_incumbency_adv": 0,
    "gop_incumbency_adv": 0,
    "is_seat_up": true
  },
  {
    "chamber_id": "ne-legislature",
    "district_number": "48",
    "incumbent_party": null,
    "is_open_seat": false,
    "dem_median": 0.24830000000000002,
    "gop_median": 0.73605,
    "dem_incumbency_adv": 0,
    "gop_incumbency_adv": 0,
    "is_seat_up": true
  },
  {
    "chamber_id": "ne-legislature",
    "district_number": "49",
    "incumbent_party": null,
    "is_open_seat": false,
    "dem_median": 0.4316,
    "gop_median": 0.5507,
    "dem_incumbency_adv": 0,
    "gop_incumbency_adv": 0,
    "is_seat_up": true
  }
]